causal_pipe/__init__.py
causal_pipe/causal_pipe.py
causal_pipe/pipe_config.py
causal_pipe/causal_discovery/__init__.py
causal_pipe/causal_discovery/bootstrap_utils.py
causal_pipe/causal_discovery/fas_bootstrap.py
causal_pipe/causal_discovery/static_causal_discovery.py
causal_pipe/datasets/__init__.py
causal_pipe/datasets/example_datasets.py
causal_pipe/fa/__init__.py
causal_pipe/hill_climber/__init__.py
causal_pipe/hill_climber/hill_climber.py
causal_pipe/imputation/__init__.py
causal_pipe/imputation/imputation.py
causal_pipe/imputation/pooled_multiple_imputation.py
causal_pipe/partial_correlations/__init__.py
causal_pipe/partial_correlations/compare_correlation_methods.py
causal_pipe/partial_correlations/partial_correlation_example.py
causal_pipe/partial_correlations/partial_correlations.py
causal_pipe/preprocess/__init__.py
causal_pipe/preprocess/factor_analysis.py
causal_pipe/preprocess/utilities.py
causal_pipe/pysr/__init__.py
causal_pipe/pysr/cyclic_scm.py
causal_pipe/pysr/pysr_helpers.py
causal_pipe/pysr/pysr_hill_climber.py
causal_pipe/pysr/pysr_regression.py
causal_pipe/pysr/pysr_utilities.py
causal_pipe/sem/__init__.py
causal_pipe/sem/bayesian_sem.py
causal_pipe/sem/resid_covariance_augmentation.py
causal_pipe/sem/sem.py
causal_pipe/utilities/__init__.py
causal_pipe/utilities/graph_utilities.py
causal_pipe/utilities/model_comparison_utilities.py
causal_pipe/utilities/model_selection_utilities.py
causal_pipe/utilities/plot_utilities.py
causal_pipe/utilities/utilities.py
causal_pipe/utilities/visualize_pysr_scm.py
causal_pipe-0.9.14.dist-info/licenses/LICENSE.md
examples/__init__.py
examples/easy.py
examples/easy_ordinal.py
examples/example_added_covariance.py
examples/hard.py
examples/non_linear.py
examples/pysr_example.py
examples/super_basic.py
examples/utilities.py
causal_pipe-0.9.14.dist-info/METADATA
causal_pipe-0.9.14.dist-info/WHEEL
causal_pipe-0.9.14.dist-info/top_level.txt
causal_pipe-0.9.14.dist-info/RECORD
