Metadata-Version: 2.4
Name: causal-pipe
Version: 0.9.14
Summary: A Python package streamlining the causal discovery pipeline for easy use.
Home-page: https://github.com/albertbuchard/causal-pipe
Author: Buchard, Albert
Author-email: albert.buchard@gmail.com
Classifier: Programming Language :: Python :: 3
Classifier: License :: OSI Approved :: MIT License
Classifier: Operating System :: OS Independent
Requires-Python: >=3.9.6
License-File: LICENSE.md
Requires-Dist: numpy==1.26.0
Requires-Dist: scipy>=1.4.0
Requires-Dist: scikit-learn>=0.22.0
Requires-Dist: causal-learn==0.1.3.8
Requires-Dist: bcsl-python==0.8.0
Requires-Dist: rpy2==3.5.16
Requires-Dist: npeet-plus==0.2.0
Requires-Dist: networkx==3.2.1
Requires-Dist: pandas==2.2.3
Requires-Dist: factor_analyzer==0.5.1
Requires-Dist: seaborn==0.13.2
Requires-Dist: matplotlib==3.9.2
Requires-Dist: graphviz==0.20.3
Requires-Dist: pydantic==2.9.2
Requires-Dist: pydot==3.0.2
Dynamic: author
Dynamic: author-email
Dynamic: classifier
Dynamic: description
Dynamic: description-content-type
Dynamic: home-page
Dynamic: license-file
Dynamic: requires-dist
Dynamic: requires-python
Dynamic: summary
